n/__init__.py
n/admin.php
n/cli.py
n/create_request.php
n/dashboard.php
n/db.php
n/index.php
n/login.php
n/logout.php
n/my_requests.php
n/new_request.php
n/register.php
n/requests.php
n/view_request.php
n/admin/index.php
n/admin/manage_users.php
n/admin/update_request.php
n/admin/view_requests.php
n/assets/css/style.css
n/config/database.php
n/config/database.sql
n/includes/footer.php
n/includes/functions.php
n/includes/header.php
reactz-0.1.4.dist-info/METADATA
reactz-0.1.4.dist-info/WHEEL
reactz-0.1.4.dist-info/entry_points.txt
reactz-0.1.4.dist-info/top_level.txt
reactz-0.1.4.dist-info/RECORD
