Metadata-Version: 2.4
Name: reactz
Version: 0.1.4
Summary: PHP project packaged as Python library with CLI tool
Author: katarymba
Author-email: your.email@example.com
Classifier: Programming Language :: Python :: 2.7
Classifier: Programming Language :: Python :: 3
Classifier: License :: OSI Approved :: MIT License
Classifier: Operating System :: OS Independent
Requires-Python: >=2.7
Dynamic: author
Dynamic: author-email
Dynamic: classifier
Dynamic: requires-python
Dynamic: summary
